bridgestream/__init__.py
bridgestream/bridgestream.py
bridgestream/tests/__init__.py
bridgestream/tests/test_bridgestream.py
bridgestream-1.2.1.dist-info/METADATA
bridgestream-1.2.1.dist-info/WHEEL
bridgestream-1.2.1.dist-info/top_level.txt
bridgestream-1.2.1.dist-info/RECORD
