Metadata-Version: 2.1
Name: bridgestream
Version: 1.2.1
Summary: Packet Serializer 
Home-page: https://gitlab.com/gnarly-games/python-bridgestream
Author: Gnarly Games
Author-email: gnarlygames@gmail.com
License: Apache 2
Platform: UNKNOWN
Classifier: License :: OSI Approved :: Apache Software License
Classifier: Programming Language :: Python :: 3.8
Classifier: Operating System :: POSIX
Classifier: Operating System :: MacOS :: MacOS X
Classifier: Operating System :: Microsoft :: Windows
Classifier: Topic :: Internet :: WWW/HTTP
Requires-Python: >=3.8.0
